snapsort/__init__.py
snapsort/main.py
snapsort-0.1.1.dist-info/METADATA
snapsort-0.1.1.dist-info/WHEEL
snapsort-0.1.1.dist-info/entry_points.txt
snapsort-0.1.1.dist-info/top_level.txt
snapsort-0.1.1.dist-info/RECORD
