Metadata-Version: 2.1
Name: snapsort
Version: 0.1.1
Summary: A CLI tool built in python to segregate people in the group photos .
Author: Haseen
Requires-Dist: ultralytics==8.3.5
Requires-Dist: opencv-python==4.10.0.84
Requires-Dist: tqdm==4.66.5
Requires-Dist: tf-keras==2.17.0
Requires-Dist: tensorflow==2.17.0
Requires-Dist: deepface==0.0.93
Requires-Dist: matplotlib==3.7.1
